nautobot_tools/__init__.py
nautobot_tools/field_mapping.py
nautobot_tools/model_meta.py
nautobot_tools/models.py
nautobot_tools/serializers.py
nautobot_tools/utils.py
nautobot_tools_dd-0.0.13.dist-info/LICENSE
nautobot_tools_dd-0.0.13.dist-info/METADATA
nautobot_tools_dd-0.0.13.dist-info/WHEEL
nautobot_tools_dd-0.0.13.dist-info/top_level.txt
nautobot_tools_dd-0.0.13.dist-info/RECORD
